aioyookassa/__init__.py
aioyookassa/contrib/__init__.py
aioyookassa/contrib/webhook_server.py
aioyookassa/core/__init__.py
aioyookassa/core/abc/__init__.py
aioyookassa/core/abc/client.py
aioyookassa/core/api/__init__.py
aioyookassa/core/api/base.py
aioyookassa/core/api/deals.py
aioyookassa/core/api/invoices.py
aioyookassa/core/api/payment_methods.py
aioyookassa/core/api/payments.py
aioyookassa/core/api/payouts.py
aioyookassa/core/api/personal_data.py
aioyookassa/core/api/receipts.py
aioyookassa/core/api/refunds.py
aioyookassa/core/api/sbp_banks.py
aioyookassa/core/api/self_employed.py
aioyookassa/core/api/webhooks.py
aioyookassa/core/client.py
aioyookassa/core/methods/__init__.py
aioyookassa/core/methods/base.py
aioyookassa/core/methods/deals.py
aioyookassa/core/methods/invoices.py
aioyookassa/core/methods/me.py
aioyookassa/core/methods/payment_methods.py
aioyookassa/core/methods/payments.py
aioyookassa/core/methods/payouts.py
aioyookassa/core/methods/personal_data.py
aioyookassa/core/methods/receipts.py
aioyookassa/core/methods/refunds.py
aioyookassa/core/methods/sbp_banks.py
aioyookassa/core/methods/self_employed.py
aioyookassa/core/methods/webhooks.py
aioyookassa/core/utils.py
aioyookassa/core/webhook_handler.py
aioyookassa/core/webhook_validator.py
aioyookassa/exceptions/__init__.py
aioyookassa/exceptions/authorization.py
aioyookassa/exceptions/base.py
aioyookassa/exceptions/payments.py
aioyookassa/exceptions/webhooks.py
aioyookassa/types/__init__.py
aioyookassa/types/deals.py
aioyookassa/types/enum.py
aioyookassa/types/invoice.py
aioyookassa/types/params.py
aioyookassa/types/payment.py
aioyookassa/types/payout.py
aioyookassa/types/personal_data.py
aioyookassa/types/receipt_registration.py
aioyookassa/types/refund.py
aioyookassa/types/sbp_banks.py
aioyookassa/types/settings.py
aioyookassa/types/webhook_notification.py
aioyookassa/types/webhooks.py
aioyookassa-2.2.5.dist-info/METADATA
aioyookassa-2.2.5.dist-info/WHEEL
aioyookassa-2.2.5.dist-info/licenses/LICENSE
aioyookassa-2.2.5.dist-info/RECORD
