Metadata-Version: 2.4
Name: aioyookassa
Version: 2.2.5
Summary: Asynchronous YooKassa API client library for Python using aiohttp and pydantic.
License: MIT
License-File: LICENSE
Keywords: yookassa,asyncio,aiohttp,pydantic,aioyookassa,async,asynchronous
Author: Masa
Requires-Python: >=3.8.1,<4.0
Classifier: Development Status :: 5 - Production/Stable
Classifier: Environment :: Console
Classifier: Framework :: AsyncIO
Classifier: Intended Audience :: Developers
Classifier: Intended Audience :: System Administrators
Classifier: License :: OSI Approved :: MIT License
Classifier: Programming Language :: Python :: 3
Classifier: Programming Language :: Python :: 3.9
Classifier: Programming Language :: Python :: 3.10
Classifier: Programming Language :: Python :: 3.11
Classifier: Programming Language :: Python :: 3.12
Classifier: Programming Language :: Python :: 3.13
Classifier: Programming Language :: Python :: 3.14
Classifier: Programming Language :: Python :: 3.8
Classifier: Topic :: Software Development :: Libraries :: Application Frameworks
Classifier: Typing :: Typed
Requires-Dist: aiohttp (>=3.9.0)
Requires-Dist: pydantic (>=2.0.0)
Project-URL: Documentation, https://aioyookassa.readthedocs.io/en/latest/
Project-URL: Repository, https://github.com/masasibata/aioyookassa
